Workbook

Sheet Resumen
A2: Matriz de pruebas de integración de clientes
A3: Resultados de ejecución en entorno local (09/10/2026).
A4: El reporte incluye la evaluación de respuestas HTTP, validación de reglas de negocio, manejo de excepciones y escenarios detenidos por dependencias previas.
A5: Estado | B5: Casos | I5: Cómo consultar los resultados
A6: Aprobado | B6: =COUNTIFS(Matriz!$M$7:$M$111,A6) -> 96 | I6: 1. Revisar Estado en la hoja Matriz.
A7: Reportado aprobado | B7: =COUNTIFS(Matriz!$M$7:$M$111,A7) -> 0 | I7: 2. Consultar HTTP obtenido y resumen de Tests en K:L.
A8: Pendiente | B8: =COUNTIFS(Matriz!$M$7:$M$111,A8) -> 0 | I8: 3. Usar Evidencia ID para localizar el caso en Evidencias.
A9: Fallido | B9: =COUNTIFS(Matriz!$M$7:$M$111,A9) -> 7 | I9: 4. Respuesta HTTP y Tests están pegados como texto.
A10: Bloqueado | B10: =COUNTIFS(Matriz!$M$7:$M$111,A10) -> 2 | I10: 5. Observaciones simples en R; próxima acción en T.
A11: Total de casos | B11: =SUM(B6:B10) -> 105
I12: Aprobado: todas las aserciones del caso pasaron.
A13: Aprobación confirmada / total | B13: =IF(B11=0,"",B6/B11) -> 0.91428571 | I13: Reportado aprobado: reservado para resultados anteriores sin ejecución individual.
I14: Pendiente: reservado para casos todavía no revisados.
I15: Fallido: falló una aserción. Bloqueado: una precondición impidió enviar la petición.
A16: Módulo | B16: Total | C16: Aprobado | D16: Reportado aprobado | E16: Pendiente | F16: Fallido | G16: Bloqueado
A17: Catalogos de Mexico | B17: =COUNTIFS(Matriz!$B$7:$B$111,$A17) -> 13 | C17: =COUNTIFS(Matriz!$B$7:$B$111,$A17,Matriz!$M$7:$M$111,C$16) -> 13 | D17: =COUNTIFS(Matriz!$B$7:$B$111,$A17,Matriz!$M$7:$M$111,D$16) -> 0 | E17: =COUNTIFS(Matriz!$B$7:$B$111,$A17,Matriz!$M$7:$M$111,E$16) -> 0 | F17: =COUNTIFS(Matriz!$B$7:$B$111,$A17,Matriz!$M$7:$M$111,F$16) -> 0 | G17: =COUNTIFS(Matriz!$B$7:$B$111,$A17,Matriz!$M$7:$M$111,G$16) -> 0 | I17: Se creó un perfil QA de mantenimiento distinto del cliente 6: cliente 11.
A18: Registro de clientes | B18: =COUNTIFS(Matriz!$B$7:$B$111,$A18) -> 13 | C18: =COUNTIFS(Matriz!$B$7:$B$111,$A18,Matriz!$M$7:$M$111,C$16) -> 9 | D18: =COUNTIFS(Matriz!$B$7:$B$111,$A18,Matriz!$M$7:$M$111,D$16) -> 0 | E18: =COUNTIFS(Matriz!$B$7:$B$111,$A18,Matriz!$M$7:$M$111,E$16) -> 0 | F18: =COUNTIFS(Matriz!$B$7:$B$111,$A18,Matriz!$M$7:$M$111,F$16) -> 4 | G18: =COUNTIFS(Matriz!$B$7:$B$111,$A18,Matriz!$M$7:$M$111,G$16) -> 0 | I18: Las altas ya existentes pueden devolver 409 cuando el caso espera 201.
A19: Autenticacion y seguridad | B19: =COUNTIFS(Matriz!$B$7:$B$111,$A19) -> 19 | C19: =COUNTIFS(Matriz!$B$7:$B$111,$A19,Matriz!$M$7:$M$111,C$16) -> 19 | D19: =COUNTIFS(Matriz!$B$7:$B$111,$A19,Matriz!$M$7:$M$111,D$16) -> 0 | E19: =COUNTIFS(Matriz!$B$7:$B$111,$A19,Matriz!$M$7:$M$111,E$16) -> 0 | F19: =COUNTIFS(Matriz!$B$7:$B$111,$A19,Matriz!$M$7:$M$111,F$16) -> 0 | G19: =COUNTIFS(Matriz!$B$7:$B$111,$A19,Matriz!$M$7:$M$111,G$16) -> 0 | I19: Los totales de paginación son dinámicos.
A20: Consultas y paginacion | B20: =COUNTIFS(Matriz!$B$7:$B$111,$A20) -> 35 | C20: =COUNTIFS(Matriz!$B$7:$B$111,$A20,Matriz!$M$7:$M$111,C$16) -> 35 | D20: =COUNTIFS(Matriz!$B$7:$B$111,$A20,Matriz!$M$7:$M$111,D$16) -> 0 | E20: =COUNTIFS(Matriz!$B$7:$B$111,$A20,Matriz!$M$7:$M$111,E$16) -> 0 | F20: =COUNTIFS(Matriz!$B$7:$B$111,$A20,Matriz!$M$7:$M$111,F$16) -> 0 | G20: =COUNTIFS(Matriz!$B$7:$B$111,$A20,Matriz!$M$7:$M$111,G$16) -> 0 | I20: Sofía y Nancy fueron registradas y sus consultas ejecutadas en esta corrida.
A21: Mantenimiento de clientes | B21: =COUNTIFS(Matriz!$B$7:$B$111,$A21) -> 19 | C21: =COUNTIFS(Matriz!$B$7:$B$111,$A21,Matriz!$M$7:$M$111,C$16) -> 19 | D21: =COUNTIFS(Matriz!$B$7:$B$111,$A21,Matriz!$M$7:$M$111,D$16) -> 0 | E21: =COUNTIFS(Matriz!$B$7:$B$111,$A21,Matriz!$M$7:$M$111,E$16) -> 0 | F21: =COUNTIFS(Matriz!$B$7:$B$111,$A21,Matriz!$M$7:$M$111,F$16) -> 0 | G21: =COUNTIFS(Matriz!$B$7:$B$111,$A21,Matriz!$M$7:$M$111,G$16) -> 0 | I21: Token anterior revocado: probar antes de expiresAt en otro perfil QA.
A22: Catalogo del proveedor GestoPago | B22: =COUNTIFS(Matriz!$B$7:$B$111,$A22) -> 6 | C22: =COUNTIFS(Matriz!$B$7:$B$111,$A22,Matriz!$M$7:$M$111,C$16) -> 1 | D22: =COUNTIFS(Matriz!$B$7:$B$111,$A22,Matriz!$M$7:$M$111,D$16) -> 0 | E22: =COUNTIFS(Matriz!$B$7:$B$111,$A22,Matriz!$M$7:$M$111,E$16) -> 0 | F22: =COUNTIFS(Matriz!$B$7:$B$111,$A22,Matriz!$M$7:$M$111,F$16) -> 3 | G22: =COUNTIFS(Matriz!$B$7:$B$111,$A22,Matriz!$M$7:$M$111,G$16) -> 2
I23: Casos y criterios: colección tests/bruno y documentación del proyecto.
I24: Resultados: conversación manual del 08/10/2026 y reportes identificados.
A25: Soporte disponible | B25: Casos | I25: Las pruebas Java previas no acreditan ejecución manual de toda la colección.
A26: Captura | B26: =COUNTIFS(Matriz!$Q$7:$Q$111,A26) -> 0 | I26: Las capturas originales se conservan sin modificar en evidencias/.
A27: Respuesta en conversación | B27: =COUNTIFS(Matriz!$Q$7:$Q$111,A27) -> 0 | I27: Las celdas editables K:R tienen fondo ámbar claro.
A28: Reporte del usuario | B28: =COUNTIFS(Matriz!$Q$7:$Q$111,A28) -> 0
A29: Reporte previo | B29: =COUNTIFS(Matriz!$Q$7:$Q$111,A29) -> 0
A30: Sin evidencia | B30: =COUNTIFS(Matriz!$Q$7:$Q$111,A30) -> 0

Sheet Matriz
A2: Matriz de pruebas funcionales
A3: Backend local. Estado histórico al 09/10/2026. Campos K:R editables para completar o actualizar resultados.
A6: ID | B6: Módulo | C6: Grupo | D6: Petición Bruno | E6: Método | F6: Endpoint y filtros | G6: Sesión requerida | H6: Precondiciones y pasos | I6: HTTP esperado | J6: Criterios de aceptación | K6: HTTP obtenido | L6: Resultado observado | M6: Estado | N6: Fecha ejecución | O6: Responsable | P6: Evidencia ID | Q6: Soporte | R6: Observaciones | S6: Fuente de la petición | T6: Próxima acción
A7: CP-001 | B7: Catalogos de Mexico | C7: Opciones personales | D7: Sexos | E7: GET | F7: /catalogos/sexos | G7: Pública | H7: Backend local iniciado; ejecutar la petición y revisar respuesta y Tests. | I7: 200 | J7: Lista pública con IDs y descripciones de las opciones de sexo. | K7: 200 | L7: HTTP 200; Tests: 1 aprobados, 0 fallidos. 20 ms. | M7: Aprobado | N7: 9/10/2026, 11:29:58 | O7: Agustin Parra | P7: S-001 | Q7: Respuesta y Tests | R7: Ejecución automática. | S7: tests/bruno/Catalogos/Opciones personales/Sexos.bru | T7: =IF(M7="Pendiente","Ejecutar y registrar evidencia",IF(M7="Reportado aprobado","Adjuntar evidencia individual",IF(M7="Fallido","Corregir y repetir",IF(M7="Bloqueado","Resolver precondición",IF(K7="","Registrar HTTP obtenido",IF(L7="","Registrar resultado",IF(N7="","Registrar fecha",IF(O7="","Registrar responsable",IF(P7="","Adjuntar evidencia",IF(Q7="Sin evidencia","Identificar soporte","Consolidado")))))))))) -> Consolidado
A8: CP-002 | B8: Catalogos de Mexico | C8: Opciones personales | D8: Nacionalidades | E8: GET | F8: /catalogos/nacionalidades | G8: Pública | H8: Backend local iniciado; ejecutar la petición y revisar respuesta y Tests. | I8: 200 | J8: Lista pública de nacionalidades disponibles. | K8: 200 | L8: HTTP 200; Tests: 1 aprobados, 0 fallidos. 18 ms. | M8: Aprobado | N8: 9/10/2026, 11:29:58 | O8: Agustin Parra | P8: CAT-001 | Q8: Respuesta y Tests | R8: Ejecución automática. | S8: tests/bruno/Catalogos/Opciones personales/Nacionalidades.bru | T8: =IF(M8="Pendiente","Ejecutar y registrar evidencia",IF(M8="Reportado aprobado","Adjuntar evidencia individual",IF(M8="Fallido","Corregir y repetir",IF(M8="Bloqueado","Resolver precondición",IF(K8="","Registrar HTTP obtenido",IF(L8="","Registrar resultado",IF(N8="","Registrar fecha",IF(O8="","Registrar responsable",IF(P8="","Adjuntar evidencia",IF(Q8="Sin evidencia","Identificar soporte","Consolidado")))))))))) -> Consolidado
A9: CP-003 | B9: Catalogos de Mexico | C9: Opciones personales | D9: Paises | E9: GET | F9: /catalogos/paises | G9: Pública | H9: Backend local iniciado; ejecutar la petición y revisar respuesta y Tests. | I9: 200 | J9: Lista pública de países disponibles. | K9: 200 | L9: HTTP 200; Tests: 1 aprobados, 0 fallidos. 19 ms. | M9: Aprobado | N9: 9/10/2026, 11:29:58 | O9: Agustin Parra | P9: CAT-002 | Q9: Respuesta y Tests | R9: Ejecución automática. | S9: tests/bruno/Catalogos/Opciones personales/Paises.bru | T9: =IF(M9="Pendiente","Ejecutar y registrar evidencia",IF(M9="Reportado aprobado","Adjuntar evidencia individual",IF(M9="Fallido","Corregir y repetir",IF(M9="Bloqueado","Resolver precondición",IF(K9="","Registrar HTTP obtenido",IF(L9="","Registrar resultado",IF(N9="","Registrar fecha",IF(O9="","Registrar responsable",IF(P9="","Adjuntar evidencia",IF(Q9="Sin evidencia","Identificar soporte","Consolidado")))))))))) -> Consolidado
A10: CP-004 | B10: Catalogos de Mexico | C10: Opciones personales | D10: Estados civiles | E10: GET | F10: /catalogos/estados-civiles | G10: Pública | H10: Backend local iniciado; ejecutar la petición y revisar respuesta y Tests. | I10: 200 | J10: Lista pública de estados civiles disponibles. | K10: 200 | L10: HTTP 200; Tests: 1 aprobados, 0 fallidos. 24 ms. | M10: Aprobado | N10: 9/10/2026, 11:29:58 | O10: Agustin Parra | P10: CAT-003 | Q10: Respuesta y Tests | R10: Ejecución automática. | S10: tests/bruno/Catalogos/Opciones personales/Estados civiles.bru | T10: =IF(M10="Pendiente","Ejecutar y registrar evidencia",IF(M10="Reportado aprobado","Adjuntar evidencia individual",IF(M10="Fallido","Corregir y repetir",IF(M10="Bloqueado","Resolver precondición",IF(K10="","Registrar HTTP obtenido",IF(L10="","Registrar resultado",IF(N10="","Registrar fecha",IF(O10="","Registrar responsable",IF(P10="","Adjuntar evidencia",IF(Q10="Sin evidencia","Identificar soporte","Consolidado")))))))))) -> Consolidado
A11: CP-005 | B11: Catalogos de Mexico | C11: Domicilios | D11: Codigo postal | E11: GET | F11: /catalogos/codigos-postales/37907 | G11: Pública | H11: Backend local iniciado; ejecutar la petición y revisar respuesta y Tests. | I11: 200 | J11: Consulta 37907 y verifica respuesta postal disponible. | K11: 200 | L11: HTTP 200; Tests: 1 aprobados, 0 fallidos. 77 ms. | M11: Aprobado | N11: 9/10/2026, 11:29:58 | O11: Agustin Parra | P11: CAT-004 | Q11: Respuesta y Tests | R11: Ejecución automática. | S11: tests/bruno/Catalogos/Domicilios/Codigo postal.bru | T11: =IF(M11="Pendiente","Ejecutar y registrar evidencia",IF(M11="Reportado aprobado","Adjuntar evidencia individual",IF(M11="Fallido","Corregir y repetir",IF(M11="Bloqueado","Resolver precondición",IF(K11="","Registrar HTTP obtenido",IF(L11="","Registrar resultado",IF(N11="","Registrar fecha",IF(O11="","Registrar responsable",IF(P11="","Adjuntar evidencia",IF(Q11="Sin evidencia","Identificar soporte","Consolidado")))))))))) -> Consolidado
A12: CP-006 | B12: Catalogos de Mexico | C12: Domicilios | D12: Codigo postal Sofia | E12: GET | F12: /catalogos/codigos-postales/37803 | G12: Pública | H12: Backend local iniciado; ejecutar la petición y revisar respuesta y Tests. | I12: 200 | J12: CP 37803 contiene asentamiento 110140023. | K12: 200 | L12: HTTP 200; Tests: 1 aprobados, 0 fallidos. 21 ms. | M12: Aprobado | N12: 9/10/2026, 11:29:58 | O12: Agustin Parra | P12: CAT-005 | Q12: Respuesta y Tests | R12: Ejecución automática. | S12: tests/bruno/Catalogos/Domicilios/Codigo postal Sofia.bru | T12: =IF(M12="Pendiente","Ejecutar y registrar evidencia",IF(M12="Reportado aprobado","Adjuntar evidencia individual",IF(M12="Fallido","Corregir y repetir",IF(M12="Bloqueado","Resolver precondición",IF(K12="","Registrar HTTP obtenido",IF(L12="","Registrar resultado",IF(N12="","Registrar fecha",IF(O12="","Registrar responsable",IF(P12="","Adjuntar evidencia",IF(Q12="Sin evidencia","Identificar soporte","Consolidado")))))))))) -> Consolidado
A13: CP-007 | B13: Catalogos de Mexico | C13: Domicilios | D13: Codigo postal Nancy | E13: GET | F13: /catalogos/codigos-postales/37903 | G13: Pública | H13: Backend local iniciado; ejecutar la petición y revisar respuesta y Tests. | I13: 200 | J13: CP 37903 contiene asentamiento 110333883. | K13: 200 | L13: HTTP 200; Tests: 1 aprobados, 0 fallidos. 19 ms. | M13: Aprobado | N13: 9/10/2026, 11:29:58 | O13: Agustin Parra | P13: CAT-006 | Q13: Respuesta y Tests | R13: Ejecución automática. | S13: tests/bruno/Catalogos/Domicilios/Codigo postal Nancy.bru | T13: =IF(M13="Pendiente","Ejecutar y registrar evidencia",IF(M13="Reportado aprobado","Adjuntar evidencia individual",IF(M13="Fallido","Corregir y repetir",IF(M13="Bloqueado","Resolver precondición",IF(K13="","Registrar HTTP obtenido",IF(L13="","Registrar resultado",IF(N13="","Registrar fecha",IF(O13="","Registrar responsable",IF(P13="","Adjuntar evidencia",IF(Q13="Sin evidencia","Identificar soporte","Consolidado")))))))))) -> Consolidado
A14: CP-008 | B14: Catalogos de Mexico | C14: Validaciones | D14: Sexo inexistente | E14: POST | F14: /clientes | G14: Pública | H14: Backend local iniciado; ejecutar la petición y revisar respuesta y Tests. | I14: 400 | J14: 400 VALIDACION con error en sexoId; no crear registros. | K14: 400 | L14: HTTP 400; Tests: 1 aprobados, 0 fallidos. 249 ms. | M14: Aprobado | N14: 9/10/2026, 11:29:58 | O14: Agustin Parra | P14: CAT-007 | Q14: Respuesta y Tests | R14: Ejecución automática. | S14: tests/bruno/Catalogos/Validaciones/Sexo inexistente.bru | T14: =IF(M14="Pendiente","Ejecutar y registrar evidencia",IF(M14="Reportado aprobado","Adjuntar evidencia individual",IF(M14="Fallido","Corregir y repetir",IF(M14="Bloqueado","Resolver precondición",IF(K14="","Registrar HTTP obtenido",IF(L14="","Registrar resultado",IF(N14="","Registrar fecha",IF(O14="","Registrar responsable",IF(P14="","Adjuntar evidencia",IF(Q14="Sin evidencia","Identificar soporte","Consolidado")))))))))) -> Consolidado
A15: CP-009 | B15: Catalogos de Mexico | C15: Validaciones | D15: Nacionalidad inexistente | E15: POST | F15: /clientes | G15: Pública | H15: Backend local iniciado; ejecutar la petición y revisar respuesta y Tests. | I15: 400 | J15: 400 VALIDACION con error en nacionalidadId; no crear registros. | K15: 400 | L15: HTTP 400; Tests: 1 aprobados, 0 fallidos. 25 ms. | M15: Aprobado | N15: 9/10/2026, 11:29:58 | O15: Agustin Parra | P15: CAT-008 | Q15: Respuesta y Tests | R15: Ejecución automática. | S15: tests/bruno/Catalogos/Validaciones/Nacionalidad inexistente.bru | T15: =IF(M15="Pendiente","Ejecutar y registrar evidencia",IF(M15="Reportado aprobado","Adjuntar evidencia individual",IF(M15="Fallido","Corregir y repetir",IF(M15="Bloqueado","Resolver precondición",IF(K15="","Registrar HTTP obtenido",IF(L15="","Registrar resultado",IF(N15="","Registrar fecha",IF(O15="","Registrar responsable",IF(P15="","Adjuntar evidencia",IF(Q15="Sin evidencia","Identificar soporte","Consolidado")))))))))) -> Consolidado
A16: CP-010 | B16: Catalogos de Mexico | C16: Validaciones | D16: Pais inexistente | E16: POST | F16: /clientes | G16: Pública | H16: Backend local iniciado; ejecutar la petición y revisar respuesta y Tests. | I16: 400 | J16: 400 VALIDACION con error en domicilio.paisId; no crear registros. | K16: 400 | L16: HTTP 400; Tests: 1 aprobados, 0 fallidos. 34 ms. | M16: Aprobado | N16: 9/10/2026, 11:29:58 | O16: Agustin Parra | P16: CAT-009 | Q16: Respuesta y Tests | R16: Ejecución automática. | S16: tests/bruno/Catalogos/Validaciones/Pais inexistente.bru | T16: =IF(M16="Pendiente","Ejecutar y registrar evidencia",IF(M16="Reportado aprobado","Adjuntar evidencia individual",IF(M16="Fallido","Corregir y repetir",IF(M16="Bloqueado","Resolver precondición",IF(K16="","Registrar HTTP obtenido",IF(L16="","Registrar resultado",IF(N16="","Registrar fecha",IF(O16="","Registrar responsable",IF(P16="","Adjuntar evidencia",IF(Q16="Sin evidencia","Identificar soporte","Consolidado")))))))))) -> Consolidado
A17: CP-011 | B17: Catalogos de Mexico | C17: Validaciones | D17: Estado civil inexistente | E17: POST | F17: /clientes | G17: Pública | H17: Backend local iniciado; ejecutar la petición y revisar respuesta y Tests. | I17: 400 | J17: 400 VALIDACION con error en estadoCivilId; no crear registros. | K17: 400 | L17: HTTP 400; Tests: 1 aprobados, 0 fallidos. 33 ms. | M17: Aprobado | N17: 9/10/2026, 11:29:58 | O17: Agustin Parra | P17: CAT-010 | Q17: Respuesta y Tests | R17: Ejecución automática. | S17: tests/bruno/Catalogos/Validaciones/Estado civil inexistente.bru | T17: =IF(M17="Pendiente","Ejecutar y registrar evidencia",IF(M17="Reportado aprobado","Adjuntar evidencia individual",IF(M17="Fallido","Corregir y repetir",IF(M17="Bloqueado","Resolver precondición",IF(K17="","Registrar HTTP obtenido",IF(L17="","Registrar resultado",IF(N17="","Registrar fecha",IF(O17="","Registrar responsable",IF(P17="","Adjuntar evidencia",IF(Q17="Sin evidencia","Identificar soporte","Consolidado")))))))))) -> Consolidado
A18: CP-012 | B18: Catalogos de Mexico | C18: Validaciones | D18: Id de catalogo con tipo incorrecto | E18: POST | F18: /clientes | G18: Pública | H18: Backend local iniciado; ejecutar la petición y revisar respuesta y Tests. | I18: 400 | J18: 400 JSON_INVALIDO con campo sexoId al enviar una cadena. | K18: 400 | L18: HTTP 400; Tests: 1 aprobados, 0 fallidos. 23 ms. | M18: Aprobado | N18: 9/10/2026, 11:29:58 | O18: Agustin Parra | P18: CAT-011 | Q18: Respuesta y Tests | R18: Ejecución automática. | S18: tests/bruno/Catalogos/Validaciones/Id de catalogo con tipo incorrecto.bru | T18: =IF(M18="Pendiente","Ejecutar y registrar evidencia",IF(M18="Reportado aprobado","Adjuntar evidencia individual",IF(M18="Fallido","Corregir y repetir",IF(M18="Bloqueado","Resolver precondición",IF(K18="","Registrar HTTP obtenido",IF(L18="","Registrar resultado",IF(N18="","Registrar fecha",IF(O18="","Registrar responsable",IF(P18="","Adjuntar evidencia",IF(Q18="Sin evidencia","Identificar soporte","Consolidado")))))))))) -> Consolidado
... A51: CP-045 | B51: Autenticacion y seguridad | C51: Acceso de perfiles QA | D51: Perfil Dulce | E51: GET | F51: /auth/me | G51: CLIENTE QA · tokenDulce | H51: Preparar tokenDulce; ejecutar la petición y revisar respuesta y Tests. | I51: 200 | J51: 200; identidad propia, activo true, rol CLIENTE. | K51: 200 | L51: HTTP 200; Tests: 1 aprobados, 0 fallidos. 33 ms. | M51: Aprobado | N51: 9/10/2026, 11:30:04 | O51: Agustin Parrra | P51: AUT-018 | Q51: Respuesta y Tests | R51: Ejecución automática. | S51: tests/bruno/Auth/Acceso de perfiles QA/Perfil Dulce.bru | T51: =IF(M51="Pendiente","Ejecutar y registrar evidencia",IF(M51="Reportado aprobado","Adjuntar evidencia individual",IF(M51="Fallido","Corregir y repetir",IF(M51="Bloqueado","Resolver precondición",IF(K51="","Registrar HTTP obtenido",IF(L51="","Registrar resultado",IF(N51="","Registrar fecha",IF(O51="","Registrar responsable",IF(P51="","Adjuntar evidencia",IF(Q51="Sin evidencia","Identificar soporte","Consolidado")))))))))) -> Consolidado
A52: CP-046 | B52: Consultas y paginacion | C52: Preparacion del ejecutivo | D52: Registro ejecutivo de prueba | E52: POST | F52: /clientes | G52: Pública | H52: El ejecutivo existente es cliente 5 / usuario 4: no repetir alta. En una instalación nueva, alta y scripts/asignar-ejecutivo.sql antes de usar su sesión. | I52: 201 inicial / 409 repetido | J52: 201 en primera alta o 409 si ya existe. El alta crea CLIENTE; asignar EJECUTIVO por el procedimiento administrativo. | K52: 409 | L52: HTTP 409; Tests: 1 aprobados, 0 fallidos. 37 ms. | M52: Aprobado | N52: 9/10/2026, 11:30:04 | O52: Agustin Parrra | P52: CON-001 | Q52: Respuesta y Tests | R52: Ejecución automática. | S52: tests/bruno/Consultas/Preparacion del ejecutivo/Registro ejecutivo de prueba.bru | T52: =IF(M52="Pendiente","Ejecutar y registrar evidencia",IF(M52="Reportado aprobado","Adjuntar evidencia individual",IF(M52="Fallido","Corregir y repetir",IF(M52="Bloqueado","Resolver precondición",IF(K52="","Registrar HTTP obtenido",IF(L52="","Registrar resultado",IF(N52="","Registrar fecha",IF(O52="","Registrar responsable",IF(P52="","Adjuntar evidencia",IF(Q52="Sin evidencia","Identificar soporte","Consolidado")))))))))) -> Consolidado
A53: CP-047 | B53: Consultas y paginacion | C53: Preparacion del ejecutivo | D53: Login ejecutivo | E53: POST | F53: /auth/login | G53: Pública | H53: Perfil correspondiente registrado y activo; usar credenciales QA de la petición. Ejecutar login y capturar JWT. | I53: 200 | J53: 200; capturar tokenEjecutivo. | K53: 200 | L53: HTTP 200; Tests: 1 aprobados, 0 fallidos. 238 ms. | M53: Aprobado | N53: 9/10/2026, 11:30:04 | O53: Agustín | P53: E-007 | Q53: Respuesta y Tests | R53: Ejecución automática. | S53: tests/bruno/Consultas/Preparacion del ejecutivo/Login ejecutivo.bru | T53: =IF(M53="Pendiente","Ejecutar y registrar evidencia",IF(M53="Reportado aprobado","Adjuntar evidencia individual",IF(M53="Fallido","Corregir y repetir",IF(M53="Bloqueado","Resolver precondición",IF(K53="","Registrar HTTP obtenido",IF(L53="","Registrar resultado",IF(N53="","Registrar fecha",IF(O53="","Registrar responsable",IF(P53="","Adjuntar evidencia",IF(Q53="Sin evidencia","Identificar soporte","Consolidado")))))))))) -> Consolidado
A54: CP-048 | B54: Consultas y paginacion | C54: Preparacion del ejecutivo | D54: Perfil ejecutivo | E54: GET | F54: /auth/me | G54: EJECUTIVO · tokenEjecutivo | H54: Login ejecutivo → Perfil ejecutivo → Ficha del ejecutivo; JWT vigente y rol EJECUTIVO; ejecutar la petición. | I54: 200 | J54: 200; rol EJECUTIVO, identidad ejecutiva activa. | K54: 200 | L54: HTTP 200; Tests: 2 aprobados, 0 fallidos. 34 ms. | M54: Aprobado | N54: 9/10/2026, 11:30:04 | O54: Agustín | P54: E-008 | Q54: Respuesta y Tests | R54: Ejecución automática. | S54: tests/bruno/Consultas/Preparacion del ejecutivo/Perfil ejecutivo.bru | T54: =IF(M54="Pendiente","Ejecutar y registrar evidencia",IF(M54="Reportado aprobado","Adjuntar evidencia individual",IF(M54="Fallido","Corregir y repetir",IF(M54="Bloqueado","Resolver precondición",IF(K54="","Registrar HTTP obtenido",IF(L54="","Registrar resultado",IF(N54="","Registrar fecha",IF(O54="","Registrar responsable",IF(P54="","Adjuntar evidencia",IF(Q54="Sin evidencia","Identificar soporte","Consolidado")))))))))) -> Consolidado
A55: CP-049 | B55: Consultas y paginacion | C55: Preparacion del ejecutivo | D55: Ficha del ejecutivo | E55: GET | F55: /clientes/me | G55: EJECUTIVO · tokenEjecutivo | H55: Login ejecutivo → Perfil ejecutivo → Ficha del ejecutivo; JWT vigente y rol EJECUTIVO; ejecutar la petición. | I55: 200 | J55: 200; cliente del ejecutivo y cuenta propia. Capturar ID y número de cuenta. | K55: 200 | L55: HTTP 200; Tests: 1 aprobados, 0 fallidos. 116 ms. | M55: Aprobado | N55: 9/10/2026, 11:30:04 | O55: Agustín | P55: AUTO-CP-049 | Q55: Respuesta y Tests | R55: Ejecución automática. | S55: tests/bruno/Consultas/Preparacion del ejecutivo/Ficha del ejecutivo.bru | T55: =IF(M55="Pendiente","Ejecutar y registrar evidencia",IF(M55="Reportado aprobado","Adjuntar evidencia individual",IF(M55="Fallido","Corregir y repetir",IF(M55="Bloqueado","Resolver precondición",IF(K55="","Registrar HTTP obtenido",IF(L55="","Registrar resultado",IF(N55="","Registrar fecha",IF(O55="","Registrar responsable",IF(P55="","Adjuntar evidencia",IF(Q55="Sin evidencia","Identificar soporte","Consolidado")))))))))) -> Consolidado
A56: CP-050 | B56: Consultas y paginacion | C56: Datos propios | D56: Mi cliente | E56: GET | F56: /clientes/me | G56: CLIENTE · token | H56: Login valido → Mi cliente para capturar clienteId/numeroCuenta; mantener JWT vigente; ejecutar la petición. | I56: 200 | J56: 200; detalle del cliente autenticado y cuentas propias, sin credenciales. | K56: 200 | L56: HTTP 200; Tests: 2 aprobados, 0 fallidos. 40 ms. | M56: Aprobado | N56: 9/10/2026, 11:30:04 | O56: Agustín | P56: AUTO-CP-050 | Q56: Respuesta y Tests | R56: Ejecución automática. | S56: tests/bruno/Consultas/Datos propios/Mi cliente.bru | T56: =IF(M56="Pendiente","Ejecutar y registrar evidencia",IF(M56="Reportado aprobado","Adjuntar evidencia individual",IF(M56="Fallido","Corregir y repetir",IF(M56="Bloqueado","Resolver precondición",IF(K56="","Registrar HTTP obtenido",IF(L56="","Registrar resultado",IF(N56="","Registrar fecha",IF(O56="","Registrar responsable",IF(P56="","Adjuntar evidencia",IF(Q56="Sin evidencia","Identificar soporte","Consolidado")))))))))) -> Consolidado
A57: CP-051 | B57: Consultas y paginacion | C57: Datos propios | D57: Cliente propio por ID | E57: GET | F57: /clientes/{{clienteId}} | G57: CLIENTE · token | H57: Login valido → Mi cliente para capturar clienteId/numeroCuenta; mantener JWT vigente; ejecutar la petición. | I57: 200 | J57: 200; clienteId de la sesión, sin acceso ajeno. | K57: 200 | L57: HTTP 200; Tests: 2 aprobados, 0 fallidos. 97 ms. | M57: Aprobado | N57: 9/10/2026, 11:30:05 | O57: Agustín | P57: AUTO-CP-051 | Q57: Respuesta y Tests | R57: Ejecución automática. | S57: tests/bruno/Consultas/Datos propios/Cliente propio por ID.bru | T57: =IF(M57="Pendiente","Ejecutar y registrar evidencia",IF(M57="Reportado aprobado","Adjuntar evidencia individual",IF(M57="Fallido","Corregir y repetir",IF(M57="Bloqueado","Resolver precondición",IF(K57="","Registrar HTTP obtenido",IF(L57="","Registrar resultado",IF(N57="","Registrar fecha",IF(O57="","Registrar responsable",IF(P57="","Adjuntar evidencia",IF(Q57="Sin evidencia","Identificar soporte","Consolidado")))))))))) -> Consolidado
A58: CP-052 | B58: Consultas y paginacion | C58: Datos propios | D58: Mi cuenta | E58: GET | F58: /cuentas/{{numeroCuenta}} | G58: CLIENTE · token | H58: Login valido → Mi cliente para capturar clienteId/numeroCuenta; mantener JWT vigente; ejecutar la petición. | I58: 200 | J58: 200; cuenta del cliente autenticado. | K58: 200 | L58: HTTP 200; Tests: 2 aprobados, 0 fallidos. 65 ms. | M58: Aprobado | N58: 9/10/2026, 11:30:05 | O58: Agustín | P58: AUTO-CP-052 | Q58: Respuesta y Tests | R58: Ejecución automática. | S58: tests/bruno/Consultas/Datos propios/Mi cuenta.bru | T58: =IF(M58="Pendiente","Ejecutar y registrar evidencia",IF(M58="Reportado aprobado","Adjuntar evidencia individual",IF(M58="Fallido","Corregir y repetir",IF(M58="Bloqueado","Resolver precondición",IF(K58="","Registrar HTTP obtenido",IF(L58="","Registrar resultado",IF(N58="","Registrar fecha",IF(O58="","Registrar responsable",IF(P58="","Adjuntar evidencia",IF(Q58="Sin evidencia","Identificar soporte","Consolidado")))))))))) -> Consolidado
A59: CP-053 | B59: Consultas y paginacion | C59: Datos propios | D59: Mi saldo | E59: GET | F59: /cuentas/{{numeroCuenta}}/saldo | G59: CLIENTE · token | H59: Login valido → Mi cliente para capturar clienteId/numeroCuenta; mantener JWT vigente; ejecutar la petición. | I59: 200 | J59: 200; número de cuenta propio y saldo numérico no negativo en el fixture QA. | K59: 200 | L59: HTTP 200; Tests: 2 aprobados, 0 fallidos. 42 ms. | M59: Aprobado | N59: 9/10/2026, 11:30:05 | O59: Agustín | P59: AUTO-CP-053 | Q59: Respuesta y Tests | R59: Ejecución automática. | S59: tests/bruno/Consultas/Datos propios/Mi saldo.bru | T59: =IF(M59="Pendiente","Ejecutar y registrar evidencia",IF(M59="Reportado aprobado","Adjuntar evidencia individual",IF(M59="Fallido","Corregir y repetir",IF(M59="Bloqueado","Resolver precondición",IF(K59="","Registrar HTTP obtenido",IF(L59="","Registrar resultado",IF(N59="","Registrar fecha",IF(O59="","Registrar responsable",IF(P59="","Adjuntar evidencia",IF(Q59="Sin evidencia","Identificar soporte","Consolidado")))))))))) -> Consolidado
A60: CP-054 | B60: Consultas y paginacion | C60: Datos propios | D60: Mis cuentas | E60: GET | F60: /clientes/{{clienteId}}/cuentas | G60: CLIENTE · token | H60: Login valido → Mi cliente para capturar clienteId/numeroCuenta; mantener JWT vigente; ejecutar la petición. | I60: 200 | J60: 200; lista de cuentas, todas del cliente autenticado. | K60: 200 | L60: HTTP 200; Tests: 1 aprobados, 0 fallidos. 62 ms. | M60: Aprobado | N60: 9/10/2026, 11:30:05 | O60: Agustín | P60: AUTO-CP-054 | Q60: Respuesta y Tests | R60: Ejecución automática. | S60: tests/bruno/Consultas/Datos propios/Mis cuentas.bru | T60: =IF(M60="Pendiente","Ejecutar y registrar evidencia",IF(M60="Reportado aprobado","Adjuntar evidencia individual",IF(M60="Fallido","Corregir y repetir",IF(M60="Bloqueado","Resolver precondición",IF(K60="","Registrar HTTP obtenido",IF(L60="","Registrar resultado",IF(N60="","Registrar fecha",IF(O60="","Registrar responsable",IF(P60="","Adjuntar evidencia",IF(Q60="Sin evidencia","Identificar soporte","Consolidado")))))))))) -> Consolidado
A61: CP-055 | B61: Consultas y paginacion | C61: Listados y filtros | D61: Listado paginado ejecutivo | E61: GET | F61: /clientes?page=0&size=2&ordenarPor=id&direccion=ASC | G61: EJECUTIVO · tokenEjecutivo | H61: Login ejecutivo → Perfil ejecutivo → Ficha del ejecutivo; JWT vigente y rol EJECUTIVO; ejecutar la petición. | I61: 200 | J61: 200; page 0, size 2, totales coherentes e IDs ascendentes. Capturar IDs y totales. | K61: 200 | L61: HTTP 200; Tests: 2 aprobados, 0 fallidos. 198 ms. | M61: Aprobado | N61: 9/10/2026, 11:30:05 | O61: Agustín | P61: AUTO-CP-055 | Q61: Respuesta y Tests | R61: Ejecución automática. | S61: tests/bruno/Consultas/Listados y filtros/Listado paginado ejecutivo.bru | T61: =IF(M61="Pendiente","Ejecutar y registrar evidencia",IF(M61="Reportado aprobado","Adjuntar evidencia individual",IF(M61="Fallido","Corregir y repetir",IF(M61="Bloqueado","Resolver precondición",IF(K61="","Registrar HTTP obtenido",IF(L61="","Registrar resultado",IF(N61="","Registrar fecha",IF(O61="","Registrar responsable",IF(P61="","Adjuntar evidencia",IF(Q61="Sin evidencia","Identificar soporte","Consolidado")))))))))) -> Consolidado
A62: CP-056 | B62: Consultas y paginacion | C62: Listados y filtros | D62: Siguiente pagina ejecutivo | E62: GET | F62: /clientes?page=1&size=2&ordenarPor=id&direccion=ASC | G62: EJECUTIVO · tokenEjecutivo | H62: Listado paginado ejecutivo primero; ejecutar enseguida sin modificar clientes entre páginas; tokenEjecutivo vigente. | I62: 200 | J62: 200; page 1, size 2, mismos totales e IDs distintos de la primera página. | K62: 200 | L62: HTTP 200; Tests: 1 aprobados, 0 fallidos. 52 ms. | M62: Aprobado | N62: 9/10/2026, 11:30:05 | O62: Agustín | P62: AUTO-CP-056 | Q62: Respuesta y Tests | R62: Ejecución automática. | S62: tests/bruno/Consultas/Listados y filtros/Siguiente pagina ejecutivo.bru | T62: =IF(M62="Pendiente","Ejecutar y registrar evidencia",IF(M62="Reportado aprobado","Adjuntar evidencia individual",IF(M62="Fallido","Corregir y repetir",IF(M62="Bloqueado","Resolver precondición",IF(K62="","Registrar HTTP obtenido",IF(L62="","Registrar resultado",IF(N62="","Registrar fecha",IF(O62="","Registrar responsable",IF(P62="","Adjuntar evidencia",IF(Q62="Sin evidencia","Identificar soporte","Consolidado")))))))))) -> Consolidado
A63: CP-057 | B63: Consultas y paginacion | C63: Listados y filtros | D63: Pagina fuera del resultado | E63: GET | F63: /clientes?page={{paginaFueraResultado}}&size=2&ordenarPor=id&direccion=ASC | G63: EJECUTIVO · tokenEjecutivo | H63: Listado paginado ejecutivo primero; usar los totales capturados para determinar página fuera del resultado. | I63: 200 | J63: 200; contenido vacío, page fuera del total y totales conservados. | K63: 200 | L63: HTTP 200; Tests: 1 aprobados, 0 fallidos. 53 ms. | M63: Aprobado | N63: 9/10/2026, 11:30:05 | O63: Agustín | P63: AUTO-CP-057 | Q63: Respuesta y Tests | R63: Ejecución automática. | S63: tests/bruno/Consultas/Listados y filtros/Pagina fuera del resultado.bru | T63: =IF(M63="Pendiente","Ejecutar y registrar evidencia",IF(M63="Reportado aprobado","Adjuntar evidencia individual",IF(M63="Fallido","Corregir y repetir",IF(M63="Bloqueado","Resolver precondición",IF(K63="","Registrar HTTP obtenido",IF(L63="","Registrar resultado",IF(N63="","Registrar fecha",IF(O63="","Registrar responsable",IF(P63="","Adjuntar evidencia",IF(Q63="Sin evidencia","Identificar soporte","Consolidado")))))))))) -> Consolidado
A64: CP-058 | B64: Consultas y paginacion | C64: Listados y filtros | D64: Filtro por CURP | E64: GET | F64: /clientes?curp=LOPA040905HGTPRGA7 | G64: EJECUTIVO · tokenEjecutivo | H64: Login ejecutivo → Perfil ejecutivo → Ficha del ejecutivo; JWT vigente y rol EJECUTIVO; ejecutar la petición. | I64: 200 | J64: 200; cliente identificado por CURP. | K64: 200 | L64: HTTP 200; Tests: 2 aprobados, 0 fallidos. 52 ms. | M64: Aprobado | N64: 9/10/2026, 11:30:05 | O64: Agustín | P64: AUTO-CP-058 | Q64: Respuesta y Tests | R64: Ejecución automática. | S64: tests/bruno/Consultas/Listados y filtros/Filtro por CURP.bru | T64: =IF(M64="Pendiente","Ejecutar y registrar evidencia",IF(M64="Reportado aprobado","Adjuntar evidencia individual",IF(M64="Fallido","Corregir y repetir",IF(M64="Bloqueado","Resolver precondición",IF(K64="","Registrar HTTP obtenido",IF(L64="","Registrar resultado",IF(N64="","Registrar fecha",IF(O64="","Registrar responsable",IF(P64="","Adjuntar evidencia",IF(Q64="Sin evidencia","Identificar soporte","Consolidado")))))))))) -> Consolidado
... A108: CP-102 | B108: Catalogo del proveedor GestoPago | C108: Sincronizacion forzada | D108: Productos antes de sincronizar | E108: GET | F108: /api/gestopago/productos | G108: CLIENTE · token | H108: JWT local de Login valido; catálogo local existente. Capturar catalogoAntes. | I108: 200 | J108: 200; IDs únicos. Capturar catalogoAntes. | K108: 500 | L108: HTTP 500; Tests: 0 aprobados, 2 fallidos. 32 ms. | M108: Fallido | N108: 9/10/2026, 11:30:11 | O108: Agustín | P108: AUTO-CP-102 | Q108: Respuesta y Tests | R108: La API respondió 500. Revisar el error del servidor. | S108: tests/bruno/GestoPago/Sincronizacion forzada/Productos antes de sincronizar.bru | T108: =IF(M108="Pendiente","Ejecutar y registrar evidencia",IF(M108="Reportado aprobado","Adjuntar evidencia individual",IF(M108="Fallido","Corregir y repetir",IF(M108="Bloqueado","Resolver precondición",IF(K108="","Registrar HTTP obtenido",IF(L108="","Registrar resultado",IF(N108="","Registrar fecha",IF(O108="","Registrar responsable",IF(P108="","Adjuntar evidencia",IF(Q108="Sin evidencia","Identificar soporte","Consolidado")))))))))) -> Corregir y repetir
A109: CP-103 | B109: Catalogo del proveedor GestoPago | C109: Sincronizacion forzada | D109: Forzar sincronizacion | E109: POST | F109: /api/gestopago/productos/forzar-sincronizacion | G109: CLIENTE · token | H109: Productos antes de sincronizar; credenciales externas configuradas en backend y JWT local vigente. Consulta realmente al proveedor. | I109: 200 | J109: 200; catálogo descargado no vacío e IDs externos únicos. | K109: No ejecutado | L109: Sin HTTP; Tests no ejecutados. Ejecuta Productos antes de sincronizar antes de forzar la descarga. | M109: Bloqueado | N109: 9/10/2026, 11:30:11 | O109: Agustín | P109: AUTO-CP-103 | Q109: Respuesta y Tests | R109: No enviado: falló la precondición del catálogo. | S109: tests/bruno/GestoPago/Sincronizacion forzada/Forzar sincronizacion.bru | T109: =IF(M109="Pendiente","Ejecutar y registrar evidencia",IF(M109="Reportado aprobado","Adjuntar evidencia individual",IF(M109="Fallido","Corregir y repetir",IF(M109="Bloqueado","Resolver precondición",IF(K109="","Registrar HTTP obtenido",IF(L109="","Registrar resultado",IF(N109="","Registrar fecha",IF(O109="","Registrar responsable",IF(P109="","Adjuntar evidencia",IF(Q109="Sin evidencia","Identificar soporte","Consolidado")))))))))) -> Resolver precondición
A110: CP-104 | B110: Catalogo del proveedor GestoPago | C110: Sincronizacion forzada | D110: Productos despues de sincronizar | E110: GET | F110: /api/gestopago/productos | G110: CLIENTE · token | H110: Antes → Forzar sincronizacion → Después, sin omitir capturas de variables. Repetir el ciclo para verificar idempotencia. | I110: 200 | J110: 200; IDs únicos, conserva ID local/fecha de creación y refleja campos descargados. | K110: No ejecutado | L110: Sin HTTP; Tests no ejecutados. Ejecuta Productos antes de sincronizar y Forzar sincronizacion en ese orden. | M110: Bloqueado | N110: 9/10/2026, 11:30:11 | O110: Agustín | P110: AUTO-CP-104 | Q110: Respuesta y Tests | R110: No enviado: falló la precondición del catálogo. | S110: tests/bruno/GestoPago/Sincronizacion forzada/Productos despues de sincronizar.bru | T110: =IF(M110="Pendiente","Ejecutar y registrar evidencia",IF(M110="Reportado aprobado","Adjuntar evidencia individual",IF(M110="Fallido","Corregir y repetir",IF(M110="Bloqueado","Resolver precondición",IF(K110="","Registrar HTTP obtenido",IF(L110="","Registrar resultado",IF(N110="","Registrar fecha",IF(O110="","Registrar responsable",IF(P110="","Adjuntar evidencia",IF(Q110="Sin evidencia","Identificar soporte","Consolidado")))))))))) -> Resolver precondición
A111: CP-105 | B111: Catalogo del proveedor GestoPago | C111: Sincronizacion forzada | D111: Sincronizacion sin token | E111: POST | F111: /api/gestopago/productos/forzar-sincronizacion | G111: Sin token | H111: Backend iniciado; ejecutar sin Bearer local. No usar el JWT del proveedor. | I111: 401 | J111: 401 NO_AUTENTICADO; no permitir sincronización sin JWT local. | K111: 401 | L111: HTTP 401; Tests: 1 aprobados, 0 fallidos. 6 ms. | M111: Aprobado | N111: 9/10/2026, 11:30:11 | O111: Agustín | P111: AUTO-CP-105 | Q111: Respuesta y Tests | R111: Ejecución automática. | S111: tests/bruno/GestoPago/Sincronizacion forzada/Sincronizacion sin token.bru | T111: =IF(M111="Pendiente","Ejecutar y registrar evidencia",IF(M111="Reportado aprobado","Adjuntar evidencia individual",IF(M111="Fallido","Corregir y repetir",IF(M111="Bloqueado","Resolver precondición",IF(K111="","Registrar HTTP obtenido",IF(L111="","Registrar resultado",IF(N111="","Registrar fecha",IF(O111="","Registrar responsable",IF(P111="","Adjuntar evidencia",IF(Q111="Sin evidencia","Identificar soporte","Consolidado")))))))))) -> Consolidado

Sheet Evidencias
A2: Índice de evidencias
A3: Resultados de ejecución automática. Respuestas y Tests pegados en texto; tokens y contraseñas omitidos.
A5: Evidencia ID | B5: Caso o bloque | C5: Tipo de soporte | D5: Respuesta HTTP | E5: Tests | F5: Observaciones
A6: S-001 | B6: CP-001 — Sexos | C6: Respuesta y Tests | D6: HTTP 200 [ { "id": 1, "descripcion": "Masculino" }, { "id": 2, "descripcion": "Femenino" } ] | E6: Tests (1), Passed: 1, Failed: 0 PASS — Catálogo disponible | F6: Ejecución automática.
A7: CAT-001 | B7: CP-002 — Nacionalidades | C7: Respuesta y Tests | D7: HTTP 200 [ { "id": 1, "descripcion": "Mexicana" } ] | E7: Tests (1), Passed: 1, Failed: 0 PASS — Catálogo disponible | F7: Ejecución automática.
A8: CAT-002 | B8: CP-003 — Paises | C8: Respuesta y Tests | D8: HTTP 200 [ { "id": 1, "descripcion": "México" } ] | E8: Tests (1), Passed: 1, Failed: 0 PASS — Catálogo disponible | F8: Ejecución automática.
A9: CAT-003 | B9: CP-004 — Estados civiles | C9: Respuesta y Tests | D9: HTTP 200 [ { "id": 1, "descripcion": "Soltero/a" }, { "id": 2, "descripcion": "Casado/a" }, { "id": 3, "descripcion": "Divorciado/a" }, { "id": 4, "descripcion": "Viudo/a" }, { "id": 5, "descripcion": "Unión libre" }, { "id": 6, "descripcion": "Separado/a" }, { "id": 7, "descripcion": "No especificado" } ] | E9: Tests (1), Passed: 1, Failed: 0 PASS — Catálogo disponible | F9: Ejecución automática.
A10: CAT-004 | B10: CP-005 — Codigo postal | C10: Respuesta y Tests | D10: HTTP 200 [ { "id": 110330007, "codigoPostal": "37907", "colonia": "Ancona Residencial", "tipo": "Fraccionamiento", "municipioId": 11033, "municipio": "San Luis de la Paz", "estadoId": 11, "estado": "Guanajuato" }, { "id": 110330008, "codigoPostal": "37907", "colonia": "Catania", "tipo": "Fraccionamiento", "municipioId": 11033, "municipio": "San Luis de la Paz", "estadoId": 11, "estado": "Guanajuato" }, { "id": 110333873, "codigoPostal": "37907", "colonia": "El Panteón", "tipo": "Colonia", "municipioId": 11033, "municipio": "San Luis de la Paz", "estadoId": 11, "estado": "Guanajuato" }, { "id": 110333854, "codigoPostal": "37907", "colonia": "La Purísima", "tipo": "Colonia", "municipioId": 11033, "municipio": "San Luis de la Paz", "estadoId": 11, "estado": "Guanajuato" }, { "id": 110330006, "codigoPostal": "37907", "colonia": "La Toscana", "tipo": "Fraccionamiento", "municipioId": 11033, "municipio": "San Luis de la Paz", "estadoId": 11, "estado": "Guanajuato" }, { "id": 110333853, "codigoPostal": "37907", "colonia": "La Virgencita", "tipo": "Colonia", "municipioId": 11033, "municipio": "San Luis de la Paz", "estadoId": 11, "estado": "Guanajuato" }, { "id": 110333890, "codigoPostal": "37907", "colonia": "Lindavista", "tipo": "Colonia", "municipioId": 11033, "municipio": "San Luis de la Paz", "estadoId": 11, "estado": "Guanajuato" }, { "id": 110333874, "codigoPostal": "37907", "colonia": "Los Pinos", "tipo": "Colonia", "municipioId": 11033, "municipio": "San Luis de la Paz", "estadoId": 11, "estado": "Guanajuato" }, { "id": 110338607, "codigoPostal": "37907", "colonia": "Los Sauces (El Derramadero)", "tipo": "Colonia", "municipioId": 11033, "municipio": "San Luis de la Paz", "estadoId": 11, "estado": "Guanajuato" }, { "id": 110338786, "codigoPostal": "37907", "colonia": "Nuevo San Luis", "tipo": "Colonia", "municipioId": 11033, "municipio": "San Luis de la Paz", "estadoId": 11, "estado": "Guanajuato" }, { "id": 110333891, "codigoPostal": "37907", "colonia": "San Isidro", "tipo": "Colonia", "municipioId": 11033, "municipio": "San Luis de la Paz", "estadoId": 11, "estado": "Guanajuato" }, { "id": 110333896, "codigoPostal": "37907", "colonia": "San Luis Gonzaga", "tipo": "Colonia", "municipioId": 11033, "municipio": "San Luis de la Paz", "estadoId": 11, "estado": "Guanajuato" }, { "id": 110338787, "codigoPostal": "37907", "colonia": "San Luis González", "tipo": "Fraccionamiento", "municipioId": 11033, "municipio": "San Luis de la Paz", "estadoId": 11, "estado": "Guanajuato" }, { "id": 110333892, "codigoPostal": "37907", "colonia": "Siglo XXI", "tipo": "Colonia", "municipioId": 11033, "municipio": "San Luis de la Paz", "estadoId": 11, "estado": "Guanajuato" } ] | E10: Tests (1), Passed: 1, Failed: 0 PASS — Catálogo disponible | F10: Ejecución automática.
A11: CAT-005 | B11: CP-006 — Codigo postal Sofia | C11: Respuesta y Tests | D11: HTTP 200 [ { "id": 110144192, "codigoPostal": "37803", "colonia": "Arboledas", "tipo": "Colonia", "municipioId": 11014, "municipio": "Dolores Hidalgo Cuna de la Independencia Nacional", "estadoId": 11, "estado": "Guanajuato" }, { "id": 110140022, "codigoPostal": "37803", "colonia": "Gladiolas", "tipo": "Colonia", "municipioId": 11014, "municipio": "Dolores Hidalgo Cuna de la Independencia Nacional", "estadoId": 11, "estado": "Guanajuato" }, { "id": 110144190, "codigoPostal": "37803", "colonia": "Guanajuato", "tipo": "Fraccionamiento", "municipioId": 11014, "municipio": "Dolores Hidalgo Cuna de la Independencia Nacional", "estadoId": 11, "estado": "Guanajuato" }, { "id": 110140023, "codigoPostal": "37803", "colonia": "Héroes de San Cristóbal", "tipo": "Colonia", "municipioId": 11014, "municipio": "Dolores Hidalgo Cuna de la Independencia Nacional", "estadoId": 11, "estado": "Guanajuato" }, { "id": 110140014, "codigoPostal": "37803", "colonia": "La Cruz del Padre Razo (Las Crucitas)", "tipo": "Colonia", "municipioId": 11014, "municipio": "Dolores Hidalgo Cuna de la Independencia Nacional", "estadoId": 11, "estado": "Guanajuato" }, { "id": 110140045, "codigoPostal": "37803", "colonia": "La Providencia", "tipo": "Colonia", "municipioId": 11014, "municipio": "Dolores Hidalgo Cuna de la Independencia Nacional", "estadoId": 11, "estado": "Guanajuato" }, { "id": 110140027, "codigoPostal": "37803", "colonia": "Lomas Verde", "tipo": "Colonia", "municipioId": 11014, "municipio": "Dolores Hidalgo Cuna de la Independencia Nacional", "estadoId": 11, "estado": "Guanajuato" }, { "id": 110145303, "codigoPostal": "37803", "colonia": "Los Olivos", "tipo": "Fraccionamiento", "municipioId": 11014, "municipio": "Dolores Hidalgo Cuna de la Independencia Nacional", "estadoId": 11, "estado": "Guanajuato" }, { "id": 110140026, "codigoPostal": "37803", "colonia": "Lázaro Cárdenas", "tipo": "Colonia", "municipioId": 11014, "municipio": "Dolores Hidalgo Cuna de la Independencia Nacional", "estadoId": 11, "estado": "Guanajuato" }, { "id": 110140028, "codigoPostal": "37803", "colonia": "Margaritas", "tipo": "Colonia", "municipioId": 11014, "municipio": "Dolores Hidalgo Cuna de la Independencia Nacional", "estadoId": 11, "estado": "Guanajuato" }, { "id": 110144188, "codigoPostal": "37803", "colonia": "Margaritas II", "tipo": "Fraccionamiento", "municipioId": 11014, "municipio": "Dolores Hidalgo Cuna de la Independencia Nacional", "estadoId": 11, "estado": "Guanajuato" }, { "id": 110144187, "codigoPostal": "37803", "colonia": "Mariano Balleza", "tipo": "Colonia", "municipioId": 11014, "municipio": "Dolores Hidalgo Cuna de la Independencia Nacional", "estadoId": 11, "estado": "Guanajuato" }, { "id": 110140006, "codigoPostal": "37803", "colonia": "Nuevo Milenio", "tipo": "Colonia", "municipioId": 11014, "municipio": "Dolores Hidalgo Cuna de la Independencia Nacional", "estadoId": 11, "estado": "Guanajuato" }, { "id": 110140047, "codigoPostal": "37803", "colonia": "Rancho Verde", "tipo": "Colonia", "municipioId": 11014, "municipio": "Dolores Hidalgo Cuna de la Independencia Nacional", "estadoId": 11, "estado": "Guanajuato" }, { "id": 110144191, "codigoPostal": "37803", "colonia": "SOP", "tipo": "Colonia", "municipioId": 11014, "municipio": "Dolores Hidalgo Cuna de la Independencia Nacional", "estadoId": 11, "estado": "Guanajuato" }, { "id": 110144189, "codigoPostal": "37803", "colonia": "San Antonio del Carmen", "tipo": "Colonia", "municipioId": 11014, "municipio": "Dolores Hidalgo Cuna de la Independencia Nacional", "estadoId": 11, "estado": "Guanajuato" }, { "id": 110140034, "codigoPostal": "37803", "colonia": "Todos los Santos", "tipo": "Fraccionamiento", "municipioId": 11014, "municipio": "Dolores Hidalgo Cuna de la Independencia Nacional", "estadoId": 11, "estado": "Guanajuato" }, { "id": 110140010, "codigoPostal": "37803", "colonia": "Universidad", "tipo": "Colonia", "municipioId": 11014, "municipio": "Dolores Hidalgo Cuna de la Independencia Nacional", "estadoId": 11, "estado": "Guanajuato" }, { "id": 110140011, "codigoPostal": "37803", "colonia": "Valle Verde", "tipo": "Fraccionamiento", "municipioId": 11014, "municipio": "Dolores Hidalgo Cuna de la Independencia Nacional", "estadoId": 11, "estado": "Guanajuato" }, { "id": 110144196, "codigoPostal": "37803", "colonia": "Vista Hermosa", "tipo": "Colonia", "municipioId": 11014, "municipio": "Dolores Hidalgo Cuna de la Independencia Nacional", "estadoId": 11, "estado": "Guanajuato" } ] | E11: Tests (1), Passed: 1, Failed: 0 PASS — Asentamiento esperado | F11: Ejecución automática.
A12: CAT-006 | B12: CP-007 — Codigo postal Nancy | C12: Respuesta y Tests | D12: HTTP 200 [ { "id": 110333876, "codigoPostal": "37903", "colonia": "Banda de Abajo", "tipo": "Colonia", "municipioId": 11033, "municipio": "San Luis de la Paz", "estadoId": 11, "estado": "Guanajuato" }, { "id": 110333883, "codigoPostal": "37903", "colonia": "Banda de Arriba", "tipo": "Colonia", "municipioId": 11033, "municipio": "San Luis de la Paz", "estadoId": 11, "estado": "Guanajuato" }, { "id": 110330004, "codigoPostal": "37903", "colonia": "Dos Plazas", "tipo": "Fraccionamiento", "municipioId": 11033, "municipio": "San Luis de la Paz", "estadoId": 11, "estado": "Guanajuato" }, { "id": 110333887, "codigoPostal": "37903", "colonia": "Insurgentes", "tipo": "Colonia", "municipioId": 11033, "municipio": "San Luis de la Paz", "estadoId": 11, "estado": "Guanajuato" }, { "id": 110333882, "codigoPostal": "37903", "colonia": "La Panorámica", "tipo": "Colonia", "municipioId": 11033, "municipio": "San Luis de la Paz", "estadoId": 11, "estado": "Guanajuato" }, { "id": 110338783, "codigoPostal": "37903", "colonia": "La Quinta", "tipo": "Colonia", "municipioId": 11033, "municipio": "San Luis de la Paz", "estadoId": 11, "estado": "Guanajuato" }, { "id": 110338395, "codigoPostal": "37903", "colonia": "Lomas de Santa Elena", "tipo": "Colonia", "municipioId": 11033, "municipio": "San Luis de la Paz", "estadoId": 11, "estado": "Guanajuato" }, { "id": 110333884, "codigoPostal": "37903", "colonia": "Planta Solar", "tipo": "Colonia", "municipioId": 11033, "municipio": "San Luis de la Paz", "estadoId": 11, "estado": "Guanajuato" }, { "id": 110333872, "codigoPostal": "37903", "colonia": "San Luisito", "tipo": "Colonia", "municipioId": 11033, "municipio": "San Luis de la Paz", "estadoId": 11, "estado": "Guanajuato" }, { "id": 110338788, "codigoPostal": "37903", "colonia": "Santa Cruz", "tipo": "Colonia", "municipioId": 11033, "municipio": "San Luis de la Paz", "estadoId": 11, "estado": "Guanajuato" }, { "id": 110338759, "codigoPostal": "37903", "colonia": "Santa Elena", "tipo": "Colonia", "municipioId": 11033, "municipio": "San Luis de la Paz", "estadoId": 11, "estado": "Guanajuato" }, { "id": 110338761, "codigoPostal": "37903", "colonia": "Santa Isabel", "tipo": "Colonia", "municipioId": 11033, "municipio": "San Luis de la Paz", "estadoId": 11, "estado": "Guanajuato" }, { "id": 110333875, "codigoPostal": "37903", "colonia": "Y Griega", "tipo": "Colonia", "municipioId": 11033, "municipio": "San Luis de la Paz", "estadoId": 11, "estado": "Guanajuato" } ] | E12: Tests (1), Passed: 1, Failed: 0 PASS — Asentamiento esperado | F12: Ejecución automática.
A13: CAT-007 | B13: CP-008 — Sexo inexistente | C13: Respuesta y Tests | D13: HTTP 400 { "timestamp": "2026-10-09T11:29:58.83437", "status": 400, "codigo": "VALIDACION", "mensaje": "Selecciona una opción habilitada del catálogo", "path": "/clientes", "errores": [ { "campo": "sexoId", "mensaje": "Selecciona una opción habilitada del catálogo" } ] } | E13: Tests (1), Passed: 1, Failed: 0 PASS — Rechaza catálogo inválido | F13: Ejecución automática.
A14: CAT-008 | B14: CP-009 — Nacionalidad inexistente | C14: Respuesta y Tests | D14: HTTP 400 { "timestamp": "2026-10-09T11:29:58.8808204", "status": 400, "codigo": "VALIDACION", "mensaje": "Selecciona una opción habilitada del catálogo", "path": "/clientes", "errores": [ { "campo": "nacionalidadId", "mensaje": "Selecciona una opción habilitada del catálogo" } ] } | E14: Tests (1), Passed: 1, Failed: 0 PASS — Rechaza catálogo inválido | F14: Ejecución automática.
A15: CAT-009 | B15: CP-010 — Pais inexistente | C15: Respuesta y Tests | D15: HTTP 400 { "timestamp": "2026-10-09T11:29:58.9243281", "status": 400, "codigo": "VALIDACION", "mensaje": "Selecciona una opción habilitada del catálogo", "path": "/clientes", "errores": [ { "campo": "domicilio.paisId", "mensaje": "Selecciona una opción habilitada del catálogo" } ] } | E15: Tests (1), Passed: 1, Failed: 0 PASS — Rechaza catálogo inválido | F15: Ejecución automática.
A16: CAT-010 | B16: CP-011 — Estado civil inexistente | C16: Respuesta y Tests | D16: HTTP 400 { "timestamp": "2026-10-09T11:29:58.9662583", "status": 400, "codigo": "VALIDACION", "mensaje": "Selecciona una opción habilitada del catálogo", "path": "/clientes", "errores": [ { "campo": "estadoCivilId", "mensaje": "Selecciona una opción habilitada del catálogo" } ] } | E16: Tests (1), Passed: 1, Failed: 0 PASS — Rechaza catálogo inválido | F16: Ejecución automática.
... A110: AUTO-CP-105 | B110: CP-105 — Sincronizacion sin token | C110: Respuesta y Tests | D110: HTTP 401 { "timestamp": "2026-10-09T11:30:11.9770893", "status": 401, "codigo": "NO_AUTENTICADO", "mensaje": "Token ausente, inválido o acceso no disponible", "path": "/api/gestopago/productos/forzar-sincronizacion", "errores": [] } | E110: Tests (1), Passed: 1, Failed: 0 PASS — Rechaza la sincronización sin JWT | F110: Ejecución automática.
